Math_Calculator/Calculator.py
Math_Calculator/__init__.py
Math_Calculator_Siddharth5G-2.5.0.dist-info/LICENSE
Math_Calculator_Siddharth5G-2.5.0.dist-info/METADATA
Math_Calculator_Siddharth5G-2.5.0.dist-info/WHEEL
Math_Calculator_Siddharth5G-2.5.0.dist-info/top_level.txt
Math_Calculator_Siddharth5G-2.5.0.dist-info/RECORD
