Metadata-Version: 2.1
Name: Math-Calculator-Siddharth5G
Version: 2.5.0
Summary: A Math Calculator
Home-page: https://github.com/Siddharth5G/python
Author: Siddharth Gopal
Author-email: siddharth24.gopal@gmail.com
License: UNKNOWN
Project-URL: Bug Tracker, https://github.com/Siddharth5G/python/issues
Platform: UNKNOWN
Classifier: Programming Language :: Python :: 3.9
Classifier: Development Status :: 4 - Beta
Classifier: License :: OSI Approved :: GNU General Public License v3 (GPLv3)
Classifier: Operating System :: OS Independent
Requires-Python: >=3.6
License-File: LICENSE
